chpobench/__init__.py
chpobench/base.py
chpobench/constants.py
chpobench/discrete_spaces.json
chpobench/hpobench.py
chpobench/hpolib.py
chpobench/jahs.py
chpobench/metadata/australian.csv
chpobench/metadata/blood_transfusion.csv
chpobench/metadata/car.csv
chpobench/metadata/cifar10.csv
chpobench/metadata/colorectal_histology.csv
chpobench/metadata/credit_g.csv
chpobench/metadata/fashion_mnist.csv
chpobench/metadata/kc1.csv
chpobench/metadata/naval_propulsion.csv
chpobench/metadata/parkinsons_telemonitoring.csv
chpobench/metadata/phoneme.csv
chpobench/metadata/protein_structure.csv
chpobench/metadata/segment.csv
chpobench/metadata/slice_localization.csv
chpobench/metadata/vehicle.csv
chpobench-0.0.5.dist-info/LICENSE
chpobench-0.0.5.dist-info/METADATA
chpobench-0.0.5.dist-info/WHEEL
chpobench-0.0.5.dist-info/top_level.txt
chpobench-0.0.5.dist-info/RECORD
